{
  "name": "Assassinate",
  "type": "feat",
  "img": "systems/pf2e/icons/default-icons/feats.webp",
  "system": {
    "description": {
      "value": "<p>You can perform a deadly strike against a foe that is unaware of your presence. Attempt a Strike against a foe that has not detected you. If the attack hits, treat it as a critical hit. You add your damage from precision to this Strike as normal.</p>",
      "gm": ""
    },
    "traits": {
      "value": [],
      "rarity": "common",
      "otherTags": []
    },
    "rules": [
      {
        "key": "ActiveEffectLike",
        "value": 1,
        "mode": "add",
        "path": "flags.pf2e.hopefinder.agilityFeats.count"
      }
    ],
    "slug": null,
    "level": {
      "value": 1
    },
    "onlyLevel1": false,
    "maxTakable": 1,
    "actionType": {
      "value": "action"
    },
    "actions": {
      "value": 2
    },
    "prerequisites": {
      "value": [
        {
          "value": "Precision feat"
        }
      ]
    },
    "location": null,
    "publication": {
      "title": "",
      "authors": "",
      "license": "OGL",
      "remaster": false
    },
    "_migration": {
      "version": 0.94,
      "previous": {
        "schema": 0.935,
        "foundry": "13.345",
        "system": "7.2.0"
      }
    },
    "category": "bonus",
    "subfeatures": {
      "proficiencies": {},
      "senses": {},
      "suppressedFeatures": []
    }
  },
  "effects": [],
  "flags": {
    "core": {}
  },
  "_stats": {
    "systemId": "pf2e",
    "systemVersion": "7.2.0",
    "coreVersion": "13.345",
    "compendiumSource": "Compendium.hopefinder.feats.Item.r502cSevwuLDWA0O",
    "duplicateSource": null,
    "exportSource": null
  },
  "_id": "r502cSevwuLDWA0O",
  "folder": null,
  "sort": 0,
  "ownership": {
    "default": 0,
    "wzla4PE5p61vlV6O": 3
  },
  "_key": "!items!r502cSevwuLDWA0O"
}
