{
  "name": "Liar",
  "type": "background",
  "img": "systems/pf2e/icons/default-icons/background.svg",
  "system": {
    "description": {
      "gm": "",
      "value": "<p>With the right words anything can be yours, and you will say anything to survive, even if it means putting someone else in danger with bad information. Suffice it to say, you have made some enemies.</p>\n<p><strong>Ability Modifiers:</strong> +1 Dex, +1 Cha</p>\n<p><strong>Skill:</strong> Trained in Deception</p>\n<p><strong>Feat:</strong> @Compendium[pf2e.feats-srd.B6HbYsLBWb1RR6Fx]{Charming Liar} skill feat</p>\n<p><strong>Gear:</strong> @Compendium[hopefinder.equipment.xA2tVYzG5pno7vCX]{Makeup Kit} (lets you create basic disguises)</p>"
    },
    "rules": [
      {
        "key": "ActiveEffectLike",
        "mode": "add",
        "path": "system.abilities.dex.mod",
        "value": 1
      },
      {
        "key": "ActiveEffectLike",
        "mode": "add",
        "path": "system.abilities.cha.mod",
        "value": 1
      },
      {
        "key": "GrantItem",
        "uuid": "Compendium.hopefinder.equipment.Item.xA2tVYzG5pno7vCX"
      }
    ],
    "slug": null,
    "_migration": {
      "version": 0.94,
      "lastMigration": null,
      "previous": {
        "schema": 0.935,
        "foundry": "13.345",
        "system": "7.2.0"
      }
    },
    "traits": {
      "otherTags": [],
      "value": [],
      "rarity": "common"
    },
    "publication": {
      "title": "Hopefinder Survivor's Guide",
      "authors": "",
      "license": "OGL",
      "remaster": false
    },
    "boosts": {
      "0": {
        "value": []
      },
      "1": {
        "value": []
      }
    },
    "items": {
      "OV5Vi": {
        "uuid": "Compendium.pf2e.feats-srd.Item.B6HbYsLBWb1RR6Fx",
        "img": "systems/pf2e/icons/features/feats/feats.webp",
        "name": "Charming Liar",
        "level": 1
      }
    },
    "trainedSkills": {
      "value": [
        "deception"
      ],
      "lore": [],
      "custom": ""
    }
  },
  "effects": [],
  "flags": {
    "core": {}
  },
  "_stats": {
    "systemId": "pf2e",
    "systemVersion": "7.2.0",
    "coreVersion": "13.345",
    "compendiumSource": "Compendium.hopefinder.backgrounds.Item.UBctDRGAG1fGS2YV",
    "duplicateSource": null,
    "exportSource": null
  },
  "_id": "UBctDRGAG1fGS2YV",
  "folder": null,
  "sort": 0,
  "ownership": {
    "default": 0,
    "wzla4PE5p61vlV6O": 3
  },
  "_key": "!items!UBctDRGAG1fGS2YV"
}
