{
  "name": "Z-Day Armor",
  "type": "armor",
  "img": "systems/pf2e/icons/default-icons/armor.svg",
  "system": {
    "description": {
      "gm": "",
      "value": "<p><strong>Resist</strong> 12 All</p>\n<p><strong>Break</strong> 20</p>"
    },
    "rules": [
      {
        "key": "Resistance",
        "type": "all-damage",
        "value": 12
      }
    ],
    "slug": null,
    "_migration": {
      "version": 0.94,
      "lastMigration": null,
      "previous": {
        "schema": 0.935,
        "foundry": "13.345",
        "system": "7.2.0"
      }
    },
    "traits": {
      "otherTags": [],
      "value": [
        "helmet",
        "sealed",
        "synthetic"
      ],
      "rarity": "common"
    },
    "publication": {
      "title": "Hopefinder Survivor's Guide",
      "authors": "",
      "license": "OGL",
      "remaster": false
    },
    "level": {
      "value": 0
    },
    "quantity": 1,
    "baseItem": null,
    "bulk": {
      "value": 0
    },
    "hp": {
      "value": 20,
      "max": 20
    },
    "hardness": 0,
    "price": {
      "value": {
        "gp": 20
      }
    },
    "equipped": {
      "carryType": "worn",
      "invested": null,
      "handsHeld": 0,
      "inSlot": false
    },
    "containerId": null,
    "size": "med",
    "material": {
      "type": null,
      "grade": null
    },
    "identification": {
      "status": "identified",
      "unidentified": {
        "name": "Unusual Armor",
        "img": "systems/pf2e/icons/unidentified_item_icons/armor.webp",
        "data": {
          "description": {
            "value": ""
          }
        }
      },
      "misidentified": {}
    },
    "category": "heavy",
    "group": null,
    "acBonus": 3,
    "strength": 10,
    "dexCap": 5,
    "checkPenalty": 0,
    "speedPenalty": -5,
    "runes": {
      "potency": 0,
      "resilient": 0,
      "property": []
    },
    "subitems": [],
    "dex": {
      "value": 10
    }
  },
  "effects": [],
  "flags": {},
  "_stats": {
    "systemId": "pf2e",
    "systemVersion": "7.2.0",
    "coreVersion": "13.345",
    "compendiumSource": "Compendium.hopefinder.equipment.Item.xjvoGlduVJ1q4gND",
    "duplicateSource": null,
    "exportSource": null
  },
  "_id": "xjvoGlduVJ1q4gND",
  "folder": null,
  "sort": 0,
  "ownership": {
    "default": 0,
    "wzla4PE5p61vlV6O": 3
  },
  "_key": "!items!xjvoGlduVJ1q4gND"
}
